interphase/__init__.py
interphase/addons.py
interphase/interphase.py
interphase/module.py
interphase-0.0.6.dist-info/METADATA
interphase-0.0.6.dist-info/WHEEL
interphase-0.0.6.dist-info/top_level.txt
interphase-0.0.6.dist-info/RECORD
