Metadata-Version: 2.1
Name: interphase
Version: 0.0.6
Summary: Package for genarating typescript interface with git submodule folder structure
Author-email: Rajat Sandeep <rajatsandeepsen1839@gmail.com>
Project-URL: Homepage, https://github.com/rajatsandeepsen/interphase
Project-URL: Bug Tracker, https://github.com/rajatsandeepsen/interphase/isssues
Keywords: python,api,backend,typescript,interface,git,submodule
Classifier: Programming Language :: Python :: 3
Classifier: Operating System :: OS Independent
Requires-Python: >=3.7
